Metadata-Version: 1.0
Name: stats-distrib
Version: 1.0
Summary: Gaussian & Binomial distributions implementation in Python
Home-page: UNKNOWN
Author: UNKNOWN
Author-email: UNKNOWN
License: UNKNOWN
Platform: UNKNOWN
